lume_py/.DS_Store
lume_py/__init__.py
lume_py/models/__init__.py
lume_py/models/endpoints/__init__.py
lume_py/models/endpoints/config.py
lume_py/models/endpoints/excel.py
lume_py/models/endpoints/jobs.py
lume_py/models/endpoints/mappers.py
lume_py/models/endpoints/pdf.py
lume_py/models/endpoints/pipeline.py
lume_py/models/endpoints/results.py
lume_py/models/endpoints/sdk/api_client.py
lume_py/models/endpoints/target.py
lume_py/models/endpoints/workshop.py
lume_py/models/pipeline.py
lume_py/models/result.py
lume_py/tests/source.json
lume_py/tests/target.json
lume_py/tests/test_workflow.py
lume_py/tests/~$consolidate-P&L.xlsx
lume_py-0.2.0.dist-info/METADATA
lume_py-0.2.0.dist-info/WHEEL
lume_py-0.2.0.dist-info/RECORD
